{
  "kind": "collectionType",
  "collectionName": "news_waterlab_2019s",
  "info": {
    "singularName": "news-waterlab-2019",
    "pluralName": "news-waterlab-2019s",
    "displayName": "News-waterlab-2019",
    "description": ""
  },
  "options": {
    "draftAndPublish": true
  },
  "pluginOptions": {},
  "attributes": {
    "content": {
      "type": "richtext"
    },
    "hasExternalLink": {
      "type": "boolean"
    },
    "externalLink": {
      "type": "text"
    },
    "order": {
      "type": "integer"
    },
    "year": {
      "type": "integer"
    }
  }
}
